bagel/__init__.py
bagel/chain.py
bagel/constants.py
bagel/energies.py
bagel/minimizer.py
bagel/mutation.py
bagel/state.py
bagel/system.py
bagel/utils.py
bagel/analysis/__init__.py
bagel/analysis/analyzer.py
bagel/oracles/__init__.py
bagel/oracles/base.py
bagel/oracles/embedding/__init__.py
bagel/oracles/embedding/base.py
bagel/oracles/embedding/esm2.py
bagel/oracles/folding/__init__.py
bagel/oracles/folding/base.py
bagel/oracles/folding/esmfold.py
bagel/oracles/folding/utils.py
biobagel-0.1.8.dist-info/METADATA
biobagel-0.1.8.dist-info/WHEEL
biobagel-0.1.8.dist-info/licenses/LICENSE
biobagel-0.1.8.dist-info/RECORD
