Metadata-Version: 2.4
Name: biobagel
Version: 0.1.8
Summary: Protein Engineering via Exploration of an Energy Landscape
Project-URL: Repository, https://github.com/softnanolab/bagel.git
Project-URL: Issues, https://github.com/softnanolab/bagel/issues
Author-email: Jakub Lála <jakublala@gmail.com>, Ayham Al-Saffar <ayham.saffar@gmail.com>, Stefano Angioletti-Uberti <sangiole@imperial.ac.uk>
License-Expression: MIT
License-File: LICENSE
Keywords: energy landscape,monte carlo,optimization,protein,protein design,sampling
Requires-Python: >=3.11
Requires-Dist: biotite>=1.0.1
Requires-Dist: boileroom==0.2.1
Requires-Dist: matplotlib>=3.10.0
Requires-Dist: numpy>=2.2.0
Requires-Dist: pandas>=2.2.3
Requires-Dist: pydantic>=2.10.6
Provides-Extra: dev
Requires-Dist: ipykernel>=6.29.5; extra == 'dev'
Requires-Dist: mypy>=1.14.1; extra == 'dev'
Requires-Dist: pre-commit>=3.6.0; extra == 'dev'
Requires-Dist: pytest-cov>=6.0.0; extra == 'dev'
Requires-Dist: pytest-repeat>=0.9.4; extra == 'dev'
Requires-Dist: pytest-xdist>=3.6.1; extra == 'dev'
Requires-Dist: pytest>=8.3.4; extra == 'dev'
Requires-Dist: ruff>=0.8.6; extra == 'dev'
Requires-Dist: sphinx-autodoc-typehints>=1.24.1; extra == 'dev'
Requires-Dist: sphinx-rtd-theme>=1.3.0; extra == 'dev'
Requires-Dist: sphinx>=8.1.3; extra == 'dev'
Provides-Extra: local
Requires-Dist: transformers>=4.49.0; extra == 'local'
